AUTHORS
INSTALL
LICENSE
MANIFEST.in
README.rst
requirements.txt
setup.cfg
setup.py
fabric/__init__.py
fabric/__main__.py
fabric/api.py
fabric/auth.py
fabric/colors.py
fabric/context_managers.py
fabric/decorators.py
fabric/docs.py
fabric/exceptions.py
fabric/io.py
fabric/job_queue.py
fabric/main.py
fabric/network.py
fabric/operations.py
fabric/sftp.py
fabric/state.py
fabric/task_utils.py
fabric/tasks.py
fabric/thread_handling.py
fabric/utils.py
fabric/version.py
fabric/contrib/__init__.py
fabric/contrib/console.py
fabric/contrib/django.py
fabric/contrib/files.py
fabric/contrib/project.py
fabricity.egg-info/PKG-INFO
fabricity.egg-info/SOURCES.txt
fabricity.egg-info/dependency_links.txt
fabricity.egg-info/entry_points.txt
fabricity.egg-info/requires.txt
fabricity.egg-info/top_level.txt
sites/shared_conf.py
sites/_shared_static/logo.png
sites/docs/conf.py
sites/docs/index.rst
sites/docs/running_tests.rst
sites/docs/tutorial.rst
sites/docs/api/contrib/console.rst
sites/docs/api/contrib/django.rst
sites/docs/api/contrib/files.rst
sites/docs/api/contrib/project.rst
sites/docs/api/core/colors.rst
sites/docs/api/core/context_managers.rst
sites/docs/api/core/decorators.rst
sites/docs/api/core/docs.rst
sites/docs/api/core/network.rst
sites/docs/api/core/operations.rst
sites/docs/api/core/tasks.rst
sites/docs/api/core/utils.rst
sites/docs/usage/env.rst
sites/docs/usage/execution.rst
sites/docs/usage/fab.rst
sites/docs/usage/fabfiles.rst
sites/docs/usage/interactivity.rst
sites/docs/usage/library.rst
sites/docs/usage/output_controls.rst
sites/docs/usage/parallel.rst
sites/docs/usage/ssh.rst
sites/docs/usage/tasks.rst
sites/www/changelog.rst
sites/www/conf.py
sites/www/contact.rst
sites/www/development.rst
sites/www/faq.rst
sites/www/index.rst
sites/www/installing.rst
sites/www/roadmap.rst
sites/www/troubleshooting.rst
tests/Python26SocketServer.py
tests/client.key
tests/client.key.pub
tests/fake_filesystem.py
tests/mock_streams.py
tests/private.key
tests/server.py
tests/test_context_managers.py
tests/test_contrib.py
tests/test_decorators.py
tests/test_io.py
tests/test_main.py
tests/test_network.py
tests/test_operations.py
tests/test_parallel.py
tests/test_project.py
