Metadata-Version: 2.1
Name: fabricity
Version: 1.15.1
Summary: [Fabric3 fork] Fabricity is a simple, Pythonic tool for remote execution and deployment.
Home-page: https://github.com/torico-tokyo/fabricity
Author: Jeff Forcier
Maintainer: torico
Maintainer-email: developer+pypi@torico-tokyo.com
License: UNKNOWN
Platform: UNKNOWN
Classifier: Development Status :: 5 - Production/Stable
Classifier: Environment :: Console
Classifier: Intended Audience :: Developers
Classifier: Intended Audience :: System Administrators
Classifier: License :: OSI Approved :: BSD License
Classifier: Operating System :: MacOS :: MacOS X
Classifier: Operating System :: Unix
Classifier: Operating System :: POSIX
Classifier: Programming Language :: Python :: 3.9
Classifier: Programming Language :: Python :: 3.10
Classifier: Topic :: Software Development
Classifier: Topic :: Software Development :: Build Tools
Classifier: Topic :: Software Development :: Libraries
Classifier: Topic :: Software Development :: Libraries :: Python Modules
Classifier: Topic :: System :: Clustering
Classifier: Topic :: System :: Software Distribution
Classifier: Topic :: System :: Systems Administration
License-File: LICENSE
License-File: AUTHORS
